embkit/__init__.py
embkit/__main__.py
embkit/align.py
embkit/bmeg.py
embkit/pathway.py
embkit/c_bio/__init__.py
embkit/c_bio/api.py
embkit/commands/__init__.py
embkit/commands/align.py
embkit/commands/cbio.py
embkit/commands/datasets.py
embkit/commands/matrix.py
embkit/commands/model.py
embkit/commands/protein.py
embkit/constraints/__init__.py
embkit/constraints/network_constraint.py
embkit/datasets/__init__.py
embkit/datasets/c_bio_portal.py
embkit/datasets/dataset.py
embkit/datasets/gtex.py
embkit/datasets/hugo.py
embkit/datasets/sif.py
embkit/datasets/util.py
embkit/estimator/__init__.py
embkit/estimator/vae_estimator.py
embkit/file_readers/__init__.py
embkit/file_readers/read_csv.py
embkit/layers/__init__.py
embkit/layers/constraint_info.py
embkit/layers/layer_info.py
embkit/layers/masked_linear.py
embkit/layers/pairwise_comparison_layer.py
embkit/layers/tsp.py
embkit/losses/__init__.py
embkit/losses/vae_loss.py
embkit/metrics/__init__.py
embkit/metrics/distance/__init__.py
embkit/metrics/distance/metrics.py
embkit/models/__init__.py
embkit/models/ffnn.py
embkit/models/hla2vec.py
embkit/models/protein.py
embkit/models/vae/__init__.py
embkit/models/vae/base_vae.py
embkit/models/vae/decoder.py
embkit/models/vae/encoder.py
embkit/models/vae/hla2vec.py
embkit/models/vae/net_vae.py
embkit/models/vae/pytorch.py
embkit/models/vae/rna_vae.py
embkit/models/vae/vae.py
embkit/preprocessing/__init__.py
embkit/preprocessing/loaders.py
embkit/preprocessing/normalize.py
embkit/utilities/__init__.py
embkit/utilities/kmeans.py
embkit/utilities/pca.py
embkit-0.2.dist-info/METADATA
embkit-0.2.dist-info/WHEEL
embkit-0.2.dist-info/entry_points.txt
embkit-0.2.dist-info/top_level.txt
embkit-0.2.dist-info/RECORD
