Metadata-Version: 2.4
Name: embkit
Version: 0.2
Summary: Embedding Kit for embedding models
Author-email: Kyle Ellrott <ellrott@ohsu.edu>, Raphael Kirchgaessner <kirchgae@ohsu.edu>
License: MIT
Keywords: embeddings,machine learning,deep learning
Requires-Python: >=3.8
Requires-Dist: torch>=2.0
Requires-Dist: pandas
Requires-Dist: numpy
Requires-Dist: click
Requires-Dist: scikit-learn
Requires-Dist: scipy
Requires-Dist: gripql
Requires-Dist: tqdm
Requires-Dist: biopython
Requires-Dist: fair-esm
